Metadata-Version: 2.1
Name: prisma-sdwan
Version: 5.4.3b1
Summary: Python2 and Python3 SDK for the CloudGenix AppFabric
Home-page: https://github.com/CloudGenix/sdk-python
Author: CloudGenix Developer Support
Author-email: developers@cloudgenix.com
License: MIT
Platform: UNKNOWN
Classifier: Development Status :: 5 - Production/Stable
Classifier: Intended Audience :: Developers
Classifier: License :: OSI Approved :: MIT License
Classifier: Programming Language :: Python :: 2.7
Classifier: Programming Language :: Python :: 3.6
Classifier: Programming Language :: Python :: 3.7
